multidataplotting/__init__.py
multidataplotting/plot_module.py
MultiDataPlotting-1.3.4.dist-info/LICENSE
MultiDataPlotting-1.3.4.dist-info/METADATA
MultiDataPlotting-1.3.4.dist-info/WHEEL
MultiDataPlotting-1.3.4.dist-info/top_level.txt
MultiDataPlotting-1.3.4.dist-info/RECORD
