Metadata-Version: 2.1
Name: MultiDataPlotting
Version: 1.3.4
Summary: A package for plotting multiple datasets
Home-page: http://github.com/wwang487/MultiDataPlotting
Author: Wei Wang
Author-email: wwang487@wisc.edu
License: MIT
Platform: UNKNOWN
Classifier: Programming Language :: Python :: 3
Classifier: License :: OSI Approved :: MIT License
Classifier: Operating System :: OS Independent
Requires-Python: >=3.6
License-File: LICENSE
Requires-Dist: setuptools
Requires-Dist: pytest
Requires-Dist: numpy
Requires-Dist: matplotlib
Requires-Dist: pandas
Requires-Dist: seaborn
Requires-Dist: scipy
Requires-Dist: datetime
Requires-Dist: scikit-learn
Requires-Dist: contextily
Requires-Dist: python-ternary
Requires-Dist: statsmodels
